pathmr/__init__.py
pathmr/pathmr.py
pathmr-0.0.1.dist-info/LICENSE
pathmr-0.0.1.dist-info/METADATA
pathmr-0.0.1.dist-info/WHEEL
pathmr-0.0.1.dist-info/top_level.txt
pathmr-0.0.1.dist-info/RECORD
