Metadata-Version: 2.1
Name: pathmr
Version: 0.0.1
Summary: A simple folder and file handling library
Author-email: jgusta <jgustafx@gmail.com>
Project-URL: Homepage, https://github.com/jgusta/pathmr
Classifier: Programming Language :: Python :: 3
Classifier: License :: OSI Approved :: MIT License
Classifier: Operating System :: OS Independent
Requires-Python: >=3.8
License-File: LICENSE
